slg_decorators/__init__.py
slg_decorators/decorators.py
slg_decorators/examples.py
slg_decorators/files.py
slg_decorators/logging.py
slg_decorators/profilers.py
slg_decorators-1.0.3.dist-info/METADATA
slg_decorators-1.0.3.dist-info/WHEEL
slg_decorators-1.0.3.dist-info/top_level.txt
slg_decorators-1.0.3.dist-info/RECORD
