Metadata-Version: 2.1
Name: slg-decorators
Version: 1.0.3
Summary: This is a description.
Home-page: UNKNOWN
License: UNKNOWN
Platform: UNKNOWN
Requires-Python: >=3.6.3
